{"filename":"./database.json","collections":[{"name":"notes","data":[],"idIndex":[],"binaryIndices":{"title":{"name":"title","dirty":false,"values":[]}},"constraints":null,"uniqueNames":["title"],"transforms":{},"objType":"notes","dirty":false,"cachedIndex":null,"cachedBinaryIndex":null,"cachedData":null,"adaptiveBinaryIndices":true,"transactional":false,"cloneObjects":false,"cloneMethod":"parse-stringify","asyncListeners":false,"disableChangesApi":true,"disableDeltaChangesApi":true,"autoupdate":false,"serializableIndices":true,"ttl":null,"maxId":0,"DynamicViews":[],"events":{"insert":[null],"update":[null],"pre-insert":[],"pre-update":[],"close":[],"flushbuffer":[],"error":[],"delete":[null],"warning":[null]},"changes":[]},{"name":"notes","data":[{"tilte":"title-1","description":"description-1","meta":{"revision":0,"created":1516996169190,"version":0},"$loki":1},{"tilte":"title-2","description":"description-2","meta":{"revision":0,"created":1516996169190,"version":0},"$loki":2}],"idIndex":[1,2],"binaryIndices":{"title":{"name":"title","dirty":false,"values":[1,0]}},"constraints":null,"uniqueNames":["title"],"transforms":{},"objType":"notes","dirty":true,"cachedIndex":null,"cachedBinaryIndex":null,"cachedData":null,"adaptiveBinaryIndices":true,"transactional":false,"cloneObjects":false,"cloneMethod":"parse-stringify","asyncListeners":false,"disableChangesApi":true,"disableDeltaChangesApi":true,"autoupdate":false,"serializableIndices":true,"ttl":null,"maxId":2,"DynamicViews":[],"events":{"insert":[null],"update":[null],"pre-insert":[],"pre-update":[],"close":[],"flushbuffer":[],"error":[],"delete":[null],"warning":[null]},"changes":[]}],"databaseVersion":1.5,"engineVersion":1.5,"autosave":true,"autosaveInterval":4000,"autosaveHandle":null,"throttledSaves":true,"options":{"autoload":true,"autosave":true,"autosaveInterval":4000,"serializationMethod":"normal","destructureDelimiter":"$<\n","recursiveWait":true,"recursiveWaitLimit":false,"recursiveWaitLimitDuration":2000,"started":1516996169190},"persistenceMethod":"fs","persistenceAdapter":null,"verbose":false,"events":{"init":[null],"loaded":[],"flushChanges":[],"close":[],"changes":[],"warning":[]},"ENV":"NODEJS"}